dig_flask_serve/__init__.py
dig_flask_serve/base_model_handler.py
dig_flask_serve/dig_flask.py
dig_flask_serve/static/index.html
dig_flask_serve-1.1.0.dist-info/licenses/LICENSE
dig_flask_serve-1.1.0.dist-info/METADATA
dig_flask_serve-1.1.0.dist-info/WHEEL
dig_flask_serve-1.1.0.dist-info/top_level.txt
dig_flask_serve-1.1.0.dist-info/RECORD
