Metadata-Version: 2.4
Name: dig-flask-serve
Version: 1.1.0
Summary: A lightweight and pluggable model serving framework based on Flask.
Home-page: https://gitee.com/buaa717/dig-flask-serve.git
Author: zsj
Author-email: zhaishujie2@buaa.edu.cn
Classifier: Programming Language :: Python :: 3
Classifier: License :: OSI Approved :: MIT License
Classifier: Operating System :: OS Independent
Requires-Python: >=3.6
License-File: LICENSE
Requires-Dist: flask>=2.0
Dynamic: author
Dynamic: author-email
Dynamic: classifier
Dynamic: description
Dynamic: description-content-type
Dynamic: home-page
Dynamic: license-file
Dynamic: requires-dist
Dynamic: requires-python
Dynamic: summary
